openplc_desktop/G.py
openplc_desktop/Qt.py
openplc_desktop/__init__.py
openplc_desktop/cwidgets.py
openplc_desktop/img.py
openplc_desktop/main_window.py
openplc_desktop/settings.py
openplc_desktop/ut.py
openplc_desktop/help/__init__.py
openplc_desktop/help/help_widgets.py
openplc_desktop/help/help_docs/__init__.py
openplc_desktop/help/help_docs/index.md
openplc_desktop/help/templates/__init__.py
openplc_desktop/help/templates/help_container.html
openplc_desktop/network/__init__.py
openplc_desktop/network/websocket_panel.py
openplc_desktop/programs/__init__.py
openplc_desktop/programs/program_dialog.py
openplc_desktop/programs/programs_grid.py
openplc_desktop/programs/programs_model.py
openplc_desktop/runtime/__init__.py
openplc_desktop/runtime/ini_editor.py
openplc_desktop/runtime/pyqterm_test.py
openplc_desktop/runtime/runtime_commander.py
openplc_desktop/runtime/settings_dialog.py
openplc_desktop/runtime/ssh_terminal.py
openplc_desktop/runtime/terminal_widget.py
openplc_desktop/server/__init__.py
openplc_desktop/server/server_conn.py
openplc_desktop/server/server_dialog.py
openplc_desktop/server/server_panel.py
openplc_desktop/server/servers_dialog.py
openplc_desktop/server/servers_model.py
openplc_desktop/slave_devices/__init__.py
openplc_desktop/slave_devices/modbus_widgets.py
openplc_desktop/slave_devices/slave_devices_grid.py
openplc_desktop/slave_devices/slave_devices_model.py
openplc_desktop/slave_devices/slave_dialog.py
openplc_desktop/static/__init__.py
openplc_desktop/static/example.ini
openplc_desktop/static/favicon.png
openplc_desktop/users/__init__.py
openplc_desktop/users/user_dialog.py
openplc_desktop/users/users_grid.py
openplc_desktop/users/users_model.py
openplc_desktop-0.9.8.data/scripts/openplc-desktop.py
openplc_desktop-0.9.8.dist-info/LICENSE
openplc_desktop-0.9.8.dist-info/METADATA
openplc_desktop-0.9.8.dist-info/WHEEL
openplc_desktop-0.9.8.dist-info/top_level.txt
openplc_desktop-0.9.8.dist-info/RECORD
