Metadata-Version: 2.1
Name: openplc-desktop
Version: 0.9.8
Summary: OpenPLC Desktop
Home-page: https://openplcproject.gitlab.io/openplc_desktop/
Author: Pedro Morgan
Author-email: openplc@daffodil.uk.com
License: UNKNOWN
Project-URL: Bug Tracker, https://gitlab.com/openplcproject/openplc_desktop/issues
Project-URL: Documentation, https://openplcproject.gitlab.io/openplc_desktop/
Project-URL: Source Code, https://gitlab.com/openplcproject/openplc_desktop
Platform: UNKNOWN
Classifier: Programming Language :: Python :: 3
Classifier: License :: OSI Approved :: GNU General Public License v2 (GPLv2)
Classifier: Operating System :: OS Independent
Requires-Python: >=3.4
Requires-Dist: mistune
Requires-Dist: paramiko
Requires-Dist: qtawesome
Requires-Dist: websocket-client
